ascender/app.py
ascender/commands/projects.py
ascender/commands/runner.py
ascender/launch.py
ascender/logic/projects.py
ascender/logic/runner.py
ascender/logic/versions.py
ascender/settings.py
ascender-0.2.0.dist-info/LICENSE
ascender-0.2.0.dist-info/METADATA
ascender-0.2.0.dist-info/WHEEL
ascender-0.2.0.dist-info/entry_points.txt
ascender-0.2.0.dist-info/RECORD
