Metadata-Version: 2.1
Name: ascender
Version: 0.2.0
Summary: The CLI tool for working with AscenderFramework: Installation, command execution and version management
Home-page: https://github.com/AscenderTeam/AscenderCLI
License: GPL-3.0
Author: AscenderTeam
Requires-Python: >=3.11,<4.0
Classifier: License :: OSI Approved :: GNU General Public License v3 (GPLv3)
Classifier: Programming Language :: Python :: 3
Classifier: Programming Language :: Python :: 3.11
Requires-Dist: gitpython (>=3.1.40,<4.0.0)
Requires-Dist: readchar (>=4.0.5,<5.0.0)
Requires-Dist: requests (>=2.31.0,<3.0.0)
Requires-Dist: rich (>=13.7.0,<14.0.0)
Requires-Dist: toml (>=0.10.2,<0.11.0)
Requires-Dist: typer[all] (>=0.9.0,<0.10.0)
Requires-Dist: virtualenv (>=20.25.0,<21.0.0)
Project-URL: Repository, https://github.com/AscenderTeam/AscenderCLI
